odoo/addons/account_invoice_anglo_saxon_no_cogs_deferral/README.rst
odoo/addons/account_invoice_anglo_saxon_no_cogs_deferral/__init__.py
odoo/addons/account_invoice_anglo_saxon_no_cogs_deferral/__manifest__.py
odoo/addons/account_invoice_anglo_saxon_no_cogs_deferral/i18n/account_invoice_anglo_saxon_no_cogs_deferral.pot
odoo/addons/account_invoice_anglo_saxon_no_cogs_deferral/i18n/de.po
odoo/addons/account_invoice_anglo_saxon_no_cogs_deferral/i18n/pt_BR.po
odoo/addons/account_invoice_anglo_saxon_no_cogs_deferral/models/__init__.py
odoo/addons/account_invoice_anglo_saxon_no_cogs_deferral/models/account_invoice.py
odoo/addons/account_invoice_anglo_saxon_no_cogs_deferral/readme/CONTRIBUTORS.rst
odoo/addons/account_invoice_anglo_saxon_no_cogs_deferral/readme/DESCRIPTION.rst
odoo/addons/account_invoice_anglo_saxon_no_cogs_deferral/readme/USAGE.rst
odoo/addons/account_invoice_anglo_saxon_no_cogs_deferral/static/description/icon.png
odoo/addons/account_invoice_anglo_saxon_no_cogs_deferral/static/description/index.html
odoo/addons/account_invoice_anglo_saxon_no_cogs_deferral/tests/__init__.py
odoo/addons/account_invoice_anglo_saxon_no_cogs_deferral/tests/test_account_invoice_anglo_saxon_no_cogs_deferral.py
odoo12_addon_account_invoice_anglo_saxon_no_cogs_deferral-12.0.1.0.0.99.dev7.dist-info/METADATA
odoo12_addon_account_invoice_anglo_saxon_no_cogs_deferral-12.0.1.0.0.99.dev7.dist-info/WHEEL
odoo12_addon_account_invoice_anglo_saxon_no_cogs_deferral-12.0.1.0.0.99.dev7.dist-info/top_level.txt
odoo12_addon_account_invoice_anglo_saxon_no_cogs_deferral-12.0.1.0.0.99.dev7.dist-info/RECORD
